rara_linker/__init__.py
rara_linker/config.py
rara_linker/exceptions.py
rara_linker/kata_config.py
rara_linker/linkers/base_linker.py
rara_linker/linkers/ems_linker.py
rara_linker/linkers/es_linker.py
rara_linker/linkers/linker.py
rara_linker/linkers/linking_result.py
rara_linker/linkers/loc_linker.py
rara_linker/linkers/org_linker.py
rara_linker/linkers/per_linker.py
rara_linker/linkers/viaf_linker.py
rara_linker/parsers/config.py
rara_linker/parsers/mrc_parsers/ems_parser.py
rara_linker/parsers/mrc_parsers/general_parser.py
rara_linker/parsers/mrc_parsers/mrc_converter.py
rara_linker/parsers/mrc_parsers/organization_parser.py
rara_linker/parsers/mrc_parsers/person_parser.py
rara_linker/parsers/mrc_records/ems_record.py
rara_linker/parsers/mrc_records/general_record.py
rara_linker/parsers/mrc_records/organization_record.py
rara_linker/parsers/mrc_records/person_record.py
rara_linker/parsers/mrc_records/title_record.py
rara_linker/tools/normalizers.py
rara_linker/tools/russian_transliterator.py
rara_linker/tools/vectorizer.py
tests/__init__.py
tests/test_linkers.py
tests/test_normalizers.py
tests/test_parsers.py
tests/test_data/ems_test_subset.mrc
tests/test_data/org_test_subset.mrc
tests/test_data/per_test_subset.mrc
rara_norm_linker-1.0.0.dist-info/LICENSE
rara_norm_linker-1.0.0.dist-info/METADATA
rara_norm_linker-1.0.0.dist-info/WHEEL
rara_norm_linker-1.0.0.dist-info/top_level.txt
rara_norm_linker-1.0.0.dist-info/RECORD
