Metadata-Version: 2.2
Name: rara-norm-linker
Version: 1.0.0
Summary: Link names, titles, organization, and subject indices with taxonomy entries.
License:                     GNU AFFERO GENERAL PUBLIC LICENSE
Classifier: Programming Language :: Python :: 3
Classifier: Programming Language :: Python :: 3.10
Classifier: Programming Language :: Python :: 3.11
Classifier: Programming Language :: Python :: 3.12
Classifier: Intended Audience :: Science/Research
Requires-Python: >=3.10
License-File: LICENSE
Requires-Dist: pytest
Requires-Dist: pymarc
Requires-Dist: requests
Requires-Dist: jellyfish
Requires-Dist: jsonlines
Requires-Dist: regex
Requires-Dist: FlagEmbedding
Requires-Dist: estnltk==1.7.3
Requires-Dist: nltk
Requires-Dist: huggingface-hub
Requires-Dist: rara-tools
Provides-Extra: testing
Requires-Dist: pytest>=8.0; extra == "testing"
